foojus/__init__.py
foojus/foojus.py
foojus-0.1.0.dist-info/LICENSE
foojus-0.1.0.dist-info/METADATA
foojus-0.1.0.dist-info/WHEEL
foojus-0.1.0.dist-info/RECORD
